flake8_requirements/__init__.py
flake8_requirements/checker.py
flake8_requirements/modules.py
flake8_requirements-2.3.0.dist-info/licenses/LICENSE.txt
flake8_requirements-2.3.0.dist-info/METADATA
flake8_requirements-2.3.0.dist-info/WHEEL
flake8_requirements-2.3.0.dist-info/entry_points.txt
flake8_requirements-2.3.0.dist-info/top_level.txt
flake8_requirements-2.3.0.dist-info/RECORD
