Metadata-Version: 2.4
Name: flake8-requirements
Version: 2.3.0
Summary: Package requirements checker, plugin for flake8
Author-email: Arkadiusz Bokowy <arkadiusz.bokowy@gmail.com>
Project-URL: Homepage, https://github.com/arkq/flake8-requirements
Classifier: Framework :: Flake8
Classifier: Intended Audience :: Developers
Classifier: License :: OSI Approved :: MIT License
Classifier: Programming Language :: Python
Classifier: Programming Language :: Python :: 3
Classifier: Programming Language :: Python :: 3 :: Only
Classifier: Topic :: Software Development :: Libraries :: Python Modules
Classifier: Topic :: Software Development :: Quality Assurance
Requires-Python: >=3.8
License-File: LICENSE.txt
Requires-Dist: flake8>=4.0.0
Requires-Dist: tomli>=1.2.1; python_version < "3.11"
Requires-Dist: packaging>=20.0
Provides-Extra: pyproject
Requires-Dist: Flake8-pyproject; extra == "pyproject"
Dynamic: license-file
